AuthoRex/__init__.py
AuthoRex/authorex.py
AuthoRex-1.0.2.dist-info/LICENSE
AuthoRex-1.0.2.dist-info/METADATA
AuthoRex-1.0.2.dist-info/WHEEL
AuthoRex-1.0.2.dist-info/top_level.txt
AuthoRex-1.0.2.dist-info/RECORD
