Metadata-Version: 2.1
Name: AuthoRex
Version: 1.0.2
Summary: A package for generating and authenticating OTPs using MongoDB.
Home-page: https://github.com/TraxDinosaur/AuthoRex
Author: TraxDinosaur
Keywords: OTP,authentication,MongoDB,OTP generator,OTP authenticator
Classifier: Programming Language :: Python :: 3
Classifier: License :: OSI Approved
Classifier: Operating System :: OS Independent
Requires-Python: >=3.6
License-File: LICENSE
Requires-Dist: pymongo
